README.md
setup.py
pythonRestfulNews/__init__.py
pythonRestfulNews.egg-info/PKG-INFO
pythonRestfulNews.egg-info/SOURCES.txt
pythonRestfulNews.egg-info/dependency_links.txt
pythonRestfulNews.egg-info/not-zip-safe
pythonRestfulNews.egg-info/requires.txt
pythonRestfulNews.egg-info/top_level.txt