Metadata-Version: 1.0
Name: pythonRestfulNews
Version: 0.5
Summary: Python Module to use RestfulNews
Home-page: https://github.com/restfulnews/pythonRestfulNews
Author: dolko
Author-email: oliver.dolk@live.com.au
License: MIT
Platform: UNKNOWN
